faissx/.version
faissx/__init__.py
faissx/client/__init__.py
faissx/client/client.py
faissx/client/index.py
faissx/client/optimization.py
faissx/client/recovery.py
faissx/client/timeout.py
faissx/client/transforms.py
faissx/client/indices/__init__.py
faissx/client/indices/base.py
faissx/client/indices/binary_base.py
faissx/client/indices/binary_flat.py
faissx/client/indices/binary_hash.py
faissx/client/indices/binary_ivf.py
faissx/client/indices/factory.py
faissx/client/indices/flat.py
faissx/client/indices/hnsw_flat.py
faissx/client/indices/id_map.py
faissx/client/indices/io.py
faissx/client/indices/ivf_flat.py
faissx/client/indices/ivf_pq.py
faissx/client/indices/ivf_scalar_quantizer.py
faissx/client/indices/modification.py
faissx/client/indices/pq.py
faissx/client/indices/pre_transform.py
faissx/client/indices/scalar_quantizer.py
faissx/server/__init__.py
faissx/server/auth.py
faissx/server/binary.py
faissx/server/cli.py
faissx/server/core.py
faissx/server/faiss_core.py
faissx/server/get_parameter.py
faissx/server/hnsw.py
faissx/server/hybrid.py
faissx/server/logging.py
faissx/server/persistence.py
faissx/server/protocol.py
faissx/server/response.py
faissx/server/server.py
faissx/server/specialized_operations.py
faissx/server/training.py
faissx/server/transformations.py
faissx-0.0.3.dist-info/licenses/LICENSE
faissx-0.0.3.dist-info/METADATA
faissx-0.0.3.dist-info/WHEEL
faissx-0.0.3.dist-info/entry_points.txt
faissx-0.0.3.dist-info/top_level.txt
faissx-0.0.3.dist-info/RECORD
